{"2": {"becameSuitTime": 1601310800.722, "savedBy": null, "track": "l", "numFloors": "1", "difficulty": "9", "state": "suit", "block": "2"}, "9": {"becameSuitTime": 1601310548.855, "savedBy": null, "track": "l", "numFloors": "1", "difficulty": "11", "state": "suit", "block": "9"}, "12": {"becameSuitTime": 1601310462.321, "savedBy": null, "track": "l", "numFloors": "3", "difficulty": "5", "state": "suit", "block": "12"}, "13": {"becameSuitTime": 1601310593.03, "savedBy": null, "track": "l", "numFloors": "0", "difficulty": "6", "state": "cogdo", "block": "13"}, "14": {"becameSuitTime": 1601310462.32, "savedBy": null, "track": "l", "numFloors": "1", "difficulty": "12", "state": "suit", "block": "14"}, "15": {"becameSuitTime": 1601310852.651, "savedBy": null, "track": "l", "numFloors": "5", "difficulty": "8", "state": "suit", "block": "15"}, "19": {"becameSuitTime": 1601310687.398, "savedBy": null, "track": "l", "numFloors": "1", "difficulty": "9", "state": "suit", "block": "19"}, "20": {"becameSuitTime": 1601310462.321, "savedBy": null, "track": "l", "numFloors": "1", "difficulty": "12", "state": "suit", "block": "20"}, "21": {"becameSuitTime": 1601310462.321, "savedBy": null, "track": "l", "numFloors": "4", "difficulty": "6", "state": "suit", "block": "21"}, "22": {"becameSuitTime": 1601310462.321, "savedBy": null, "track": "l", "numFloors": "1", "difficulty": "10", "state": "suit", "block": "22"}, "26": {"becameSuitTime": 1601310462.321, "savedBy": null, "track": "l", "numFloors": "3", "difficulty": "6", "state": "suit", "block": "26"}, "28": {"becameSuitTime": 1601310670.51, "savedBy": null, "track": "l", "numFloors": "0", "difficulty": "5", "state": "cogdo", "block": "28"}}