{"4": {"becameSuitTime": 1600469110.85, "savedBy": null, "track": "l", "numFloors": "1", "difficulty": "10", "state": "suit", "block": "4"}, "6": {"becameSuitTime": 1600469110.851, "savedBy": null, "track": "l", "numFloors": "1", "difficulty": "12", "state": "suit", "block": "6"}, "20": {"becameSuitTime": 1600469110.852, "savedBy": null, "track": "l", "numFloors": "1", "difficulty": "10", "state": "suit", "block": "20"}, "21": {"becameSuitTime": 1600469110.852, "savedBy": null, "track": "l", "numFloors": "1", "difficulty": "10", "state": "suit", "block": "21"}, "22": {"becameSuitTime": 1600469110.851, "savedBy": null, "track": "l", "numFloors": "1", "difficulty": "10", "state": "suit", "block": "22"}, "26": {"becameSuitTime": 1600469110.853, "savedBy": null, "track": "l", "numFloors": "1", "difficulty": "9", "state": "suit", "block": "26"}}