{"20": {"becameSuitTime": 1581310552.668, "savedBy": null, "track": "l", "numFloors": "4", "difficulty": "7", "state": "clearOutToonInterior", "block": "20"}, "10": {"becameSuitTime": 1581310552.667, "savedBy": null, "track": "l", "numFloors": "1", "difficulty": "9", "state": "clearOutToonInterior", "block": "10"}, "12": {"becameSuitTime": 1581310552.668, "savedBy": null, "track": "l", "numFloors": "5", "difficulty": "8", "state": "clearOutToonInterior", "block": "12"}, "26": {"becameSuitTime": 1581310552.668, "savedBy": null, "track": "l", "numFloors": "1", "difficulty": "9", "state": "clearOutToonInterior", "block": "26"}}