{"42": {"becameSuitTime": 1581307418.065, "savedBy": null, "track": "c", "numFloors": "3", "difficulty": "3", "state": "suit", "block": "42"}, "43": {"becameSuitTime": 1581307592.089, "savedBy": null, "track": "c", "numFloors": "1", "difficulty": "2", "state": "suit", "block": "43"}, "17": {"becameSuitTime": 1581307462.35, "savedBy": null, "track": "l", "numFloors": "4", "difficulty": "4", "state": "suit", "block": "17"}, "50": {"becameSuitTime": 1581307867.074, "savedBy": null, "track": "l", "numFloors": "0", "difficulty": "2", "state": "cogdo", "block": "50"}, "21": {"becameSuitTime": 1581307418.066, "savedBy": null, "track": "l", "numFloors": "4", "difficulty": "5", "state": "suit", "block": "21"}, "29": {"becameSuitTime": 1581307605.907, "savedBy": null, "track": "l", "numFloors": "0", "difficulty": "3", "state": "cogdo", "block": "29"}, "62": {"becameSuitTime": 1581307418.065, "savedBy": null, "track": "c", "numFloors": "4", "difficulty": "5", "state": "suit", "block": "62"}}